{"judul":"The Breaker – New Waves","slug":"the-breaker-new-waves","tipe":"","released":"","rating":"8.6","author":"","artist":"","status":"","genre":["Action","Comedy","Drama","Ecchi","Harem","Martial Arts","School Life","Shounen"],"synopsis":"Setelah pertempuran putus asa antara Goomoonryong dan Aliansi Seni Bela Diri – pusat ki Yi Shioon dihancurkan oleh tuannya sendiri Goomoonryong, membuatnya tidak dapat berlatih seni bela diri …","thumbnail":"https://kiryuu02.com/wp-content/uploads/2021/03/the-breaker-new-wave-836851-yo8gpZvx-225x300.jpg"}