{"judul":"Bouken-ka ni Narou!: Skill Board de Dungeon Kouryaku","slug":"bouken-ka-ni-narou-skill-board-de-dungeon-kouryaku","tipe":"","released":"","rating":"7.6","author":"","artist":"","status":"","genre":["Action","Adventure","Comedy","Fantasy","Shounen"],"synopsis":"Karaboshi Haruki tidak punya apa-apa sejak awal, dan karena itu dia menjadi seorang petualang dengan tujuan untuk “terkenal.” Suatu hari, sebuah dungeon muncul di bawah rumahnya di Hokkaido. Secara kebetulan, dia mengambil “Skill Board” yang dengan itu dia bisa mengeluarkan poin keterampilan untuk meningkatkan tingkat pertumbuhannya. Mungkinkah menjadi orang populer dengan masuk ke dungeon rumahmu setiap hari?","thumbnail":"https://kiryuu02.com/wp-content/uploads/2021/04/bouken-ka-ni-narou-543139-q1mdIsFD-205x300.jpg"}