{"judul":"CMYK – Sameda Kazuou wa Chuunibyou ga Naosenai","slug":"cmyk-sameda-kazuou-wa-chuunibyou-ga-naosenai","tipe":"","released":"","rating":"8.23","author":"","artist":"","status":"","genre":["Comedy","Fantasy","School Life"],"synopsis":"Sameda Kazuou, yang akhirnya lepas dari sindrom Chuunibyou-nya, ingin menghapus fakta bahwa ia pernah seperti itu, dan memutuskan untuk mengubur semua foto sekolahnya yang penuh dengan masa lalu dirinya. Namun, ada tiga gadis cantik di sekolah yang menginginkan foto-foto itu…","thumbnail":"https://kiryuu02.com/wp-content/uploads/2025/09/06913db9-9f1f-40fe-a137-6c3b13c3b470-024111-MMFI1Aqr-211x300.jpg"}