{"judul":"Chi – Chikyuu no Undou ni Tsuite","slug":"chi-chikyuu-no-undou-ni-tsuite","tipe":"","released":"","rating":"7.00","author":"","artist":"","status":"","genre":["Historical","Mature","Mystery","Psychological","Seinen","Tragedy"],"synopsis":"Berlatar pada abad ke-15 di Polandia. Saat itu adalah masa ketika ide-ide sesat membuat mereka yang memiliki pola pikir yang demikian dibakar dalam salib. Rafal, seorang anak ajaib yang diharapkan mengambil jurusan teologi, mata pelajaran terpenting saat itu, suatu hari, dia bertemu dengan seorang pria misterius, dan mulai mempelajari kemungkinan “kebenaran” dari pemikiran-pemikiran sesat!","thumbnail":"https://kiryuu02.com/wp-content/uploads/2024/01/chi-chikyuu-no-undou-ni-tsuite-644477-rAmmbWGS-212x300.webp"}