{"judul":"Boku wa Isekai de Fuyo Mahou to Shoukan Mahou wo Tenbin ni Kakeru","slug":"boku-wa-isekai-de-fuyo-mahou-to-shoukan-mahou-wo-tenbin-ni-kakeru","tipe":"","released":"","rating":"7","author":"","artist":"","status":"","genre":["Action","Adventure","Drama","Fantasy","Harem","Shounen"],"synopsis":"Suatu hari, di sekolah swasta tertentu dengan asrama, seluruh sekolah dipindahkan ke dunia lain. aku, Kaya Kazuhisa. dari kelas 1 SMA. telah diintimidasi untuk waktu yang lama. untuk membunuh pelakunya yang telah menggangguku, aku menggali jebakan. tapi tiba-tiba aku membunuh monster. sejak saat itu. aku telah berevolusi menjadi keberadaan langka yang dapat melawan monster. di hari yang sama, aku menyelamatkan seorang gadis dari kelas 3 sekolah menengah, Shimozono Arisu di hutan dari orc. ketika aku bekerja dengan arisu untuk mengalahkan orc, dan secara bertahap naik aku level. aku dipaksa untuk membuat pilihan. haruskah aku memilih sihir pemanggilan yang cocok untuk bertahan hidup sendirian? atau aku harus pilih sihir pendukung yang digunakan saat bertarung bersama dengannya?","thumbnail":"https://kiryuu02.com/wp-content/uploads/2021/10/boku-wa-isekai-de-fuyo-mahou-to-shoukan-mahou-wo-tenbin-ni-kakeru-707830-QKTYjpeP-211x300.jpeg"}